{
  "dataset_id": "ds003478:sub-020:rest_Rest_run-02",
  "samples": 41,
  "mnps": {
    "fs_out": 4.0,
    "window_sec": 8.0,
    "overlap": 0.5,
    "window_bounds": true
  },
  "mnps_axes": {
    "names": [
      "m",
      "d",
      "e"
    ],
    "meaning": {
      "m": "mobility",
      "d": "diffusivity",
      "e": "entropy"
    },
    "order": {
      "m": 0,
      "d": 1,
      "e": 2
    }
  },
  "meta_indices": {
    "mean_trace": -0.04146700252134066,
    "mean_rotation_fro": 0.057222626625727385,
    "windows": 39
  },
  "events": [],
  "labels": [],
  "jacobian": {
    "windows": 39,
    "with_centers": true
  },
  "meta_indices_v2": {
    "mean_trace": -0.049727668961844385,
    "mean_rotation_fro": 0.26625694754796153,
    "windows": 39
  },
  "jacobian_9D": {
    "windows": 39,
    "with_centers": true
  },
  "diagnostics": {
    "windows": 39.0,
    "failed": 0.0,
    "j_dot_mode": "gradient",
    "j_dot_dt": 4.0,
    "local_fit_mse_median": 0.0005805721157230437,
    "local_fit_mse_baseline_median": 0.0005681226029992104,
    "rel_mse_baseline_median": 1.0329299066889397
  },
  "coords_9d": {
    "names": [
      "m_a",
      "m_e",
      "m_o",
      "d_n",
      "d_l",
      "d_s",
      "e_e",
      "e_s",
      "e_m"
    ],
    "export_prefix": "v2_",
    "composites": {
      "m": "m_mean_from_v2",
      "d": "d_mean_from_v2",
      "e": "e_mean_from_v2"
    },
    "groups": {
      "m": [
        "m_a",
        "m_e",
        "m_o"
      ],
      "d": [
        "d_n",
        "d_l",
        "d_s"
      ],
      "e": [
        "e_e",
        "e_s",
        "e_m"
      ]
    }
  },
  "feature_baselines": {
    "eeg_alpha": {
      "abs_median": 0.3098979890346527,
      "abs_mad": 0.382525935280323,
      "transformation_applied": "log10 -> robust_z -> clip_6.0"
    },
    "eeg_alpha_theta": {
      "abs_median": 1.0591144561767578,
      "abs_mad": 1.1085233708381652,
      "transformation_applied": "robust_z -> clip_6.0"
    },
    "eeg_beta": {
      "abs_median": 0.3666572570800781,
      "abs_mad": 0.3229581636607647,
      "transformation_applied": "log10 -> robust_z -> clip_6.0"
    },
    "eeg_beta_alpha": {
      "abs_median": 1.3786790370941162,
      "abs_mad": 1.6780868253707886,
      "transformation_applied": "robust_z -> clip_6.0"
    },
    "eeg_delta": {
      "abs_median": 0.3948501646518707,
      "abs_mad": 0.3052058103382587,
      "transformation_applied": "log10 -> robust_z -> clip_6.0"
    },
    "eeg_gamma": {
      "abs_median": 0.13611198961734772,
      "abs_mad": 0.11123527897596358,
      "transformation_applied": "log10 -> robust_z -> clip_6.0"
    },
    "eeg_sample_entropy": {
      "abs_median": 0.8754132390022278,
      "abs_mad": 0.06051222435235977,
      "transformation_applied": "robust_z -> clip_6.0"
    },
    "eeg_theta": {
      "abs_median": 0.2096322923898697,
      "abs_mad": 0.167771854403615,
      "transformation_applied": "log10 -> robust_z -> clip_6.0"
    },
    "ecg_rmssd": {
      "abs_median": null,
      "abs_mad": null,
      "transformation_applied": "none"
    },
    "eeg_hjorth_complexity": {
      "abs_median": 2.5673458576202393,
      "abs_mad": 0.2381991534233093,
      "transformation_applied": "robust_z -> clip_6.0"
    },
    "eeg_hjorth_mobility": {
      "abs_median": 0.43367695808410645,
      "abs_mad": 0.1563806056380272,
      "transformation_applied": "robust_z -> clip_6.0"
    },
    "eeg_permutation_entropy": {
      "abs_median": 0.8754132390022278,
      "abs_mad": 0.06051222435235977,
      "transformation_applied": "robust_z -> clip_6.0"
    },
    "embodied_arousal_proxy": {
      "abs_median": 0.0,
      "abs_mad": 0.0,
      "transformation_applied": "robust_z -> clip_6.0"
    },
    "eog_blink_rate": {
      "abs_median": 0.0,
      "abs_mad": 0.0,
      "transformation_applied": "robust_z -> clip_6.0"
    }
  },
  "subject": "sub-020",
  "run": "run-02",
  "participant_meta": {
    "participant_id": "sub-020",
    "Original_ID": 526,
    "sex": 1.0,
    "age": 18.0,
    "BDI": 0.0,
    "STAI": 30.0,
    "SCID": "No Interview",
    "SCID_notes": null,
    "HamD": null
  },
  "group": "0.0",
  "condition": "rest",
  "task": "Rest",
  "coverage": {
    "rule_tag": "default",
    "min_seconds_effective": 60.0,
    "min_epochs_effective": 20,
    "seconds_effective": 168.0,
    "seconds_measured": 168.0,
    "seconds_assumed": 164.0,
    "seconds_method": "timestamps_span"
  },
  "created_at": "2026-03-09T13:45:28.701763Z",
  "jacobian_9D_blocks": {
    "config": {
      "enabled": true,
      "preset": "mde_families_v1",
      "groups": {
        "m": [
          "m_a",
          "m_e",
          "m_o"
        ],
        "d": [
          "d_n",
          "d_l",
          "d_s"
        ],
        "e": [
          "e_e",
          "e_s",
          "e_m"
        ]
      },
      "pairs": "all",
      "include_self": true,
      "include_sym_rot": true,
      "n_blocks": 9
    },
    "rows": [
      {
        "out_group": "m",
        "in_group": "m",
        "out_dim": 3,
        "in_dim": 3,
        "n_timepoints": 39,
        "block_trace_mean": -0.02463597792815656,
        "block_frobenius_mean": 0.13255752623081207,
        "block_anisotropy_mean": 79.45385519663493,
        "c_sym_mean": null,
        "c_rot_mean": null
      },
      {
        "out_group": "m",
        "in_group": "d",
        "out_dim": 3,
        "in_dim": 3,
        "n_timepoints": 39,
        "block_trace_mean": null,
        "block_frobenius_mean": 0.11063677072525024,
        "block_anisotropy_mean": null,
        "c_sym_mean": 0.08702807032909149,
        "c_rot_mean": 0.08742208836170343
      },
      {
        "out_group": "m",
        "in_group": "e",
        "out_dim": 3,
        "in_dim": 3,
        "n_timepoints": 39,
        "block_trace_mean": null,
        "block_frobenius_mean": 0.11817006766796112,
        "block_anisotropy_mean": null,
        "c_sym_mean": 0.10061398387337342,
        "c_rot_mean": 0.10285698163967866
      },
      {
        "out_group": "d",
        "in_group": "m",
        "out_dim": 3,
        "in_dim": 3,
        "n_timepoints": 39,
        "block_trace_mean": null,
        "block_frobenius_mean": 0.12950728833675385,
        "block_anisotropy_mean": null,
        "c_sym_mean": 0.08702807032909149,
        "c_rot_mean": 0.08742208836170343
      },
      {
        "out_group": "d",
        "in_group": "d",
        "out_dim": 3,
        "in_dim": 3,
        "n_timepoints": 39,
        "block_trace_mean": 0.008814080582501797,
        "block_frobenius_mean": 0.09907954186201096,
        "block_anisotropy_mean": 80088.71633894015,
        "c_sym_mean": null,
        "c_rot_mean": null
      },
      {
        "out_group": "d",
        "in_group": "e",
        "out_dim": 3,
        "in_dim": 3,
        "n_timepoints": 39,
        "block_trace_mean": null,
        "block_frobenius_mean": 0.08574828505516052,
        "block_anisotropy_mean": null,
        "c_sym_mean": 0.06333692433933417,
        "c_rot_mean": 0.07727231706182162
      },
      {
        "out_group": "e",
        "in_group": "m",
        "out_dim": 3,
        "in_dim": 3,
        "n_timepoints": 39,
        "block_trace_mean": null,
        "block_frobenius_mean": 0.16230639815330505,
        "block_anisotropy_mean": null,
        "c_sym_mean": 0.10061398387337342,
        "c_rot_mean": 0.10285698163967866
      },
      {
        "out_group": "e",
        "in_group": "d",
        "out_dim": 3,
        "in_dim": 3,
        "n_timepoints": 39,
        "block_trace_mean": null,
        "block_frobenius_mean": 0.10190790146589279,
        "block_anisotropy_mean": null,
        "c_sym_mean": 0.06333692433933417,
        "c_rot_mean": 0.07727231706182162
      },
      {
        "out_group": "e",
        "in_group": "e",
        "out_dim": 3,
        "in_dim": 3,
        "n_timepoints": 39,
        "block_trace_mean": -0.03390577196692809,
        "block_frobenius_mean": 0.11253593116998672,
        "block_anisotropy_mean": null,
        "c_sym_mean": null,
        "c_rot_mean": null
      }
    ]
  },
  "ensemble_robustness": {
    "groups_config": {
      "frontal": [
        "Fp1",
        "Fp2",
        "F3",
        "F4",
        "Fz",
        "F7",
        "F8"
      ],
      "central": [
        "FC1",
        "FC2",
        "C3",
        "Cz",
        "C4"
      ],
      "parietal_occipital": [
        "P3",
        "P4",
        "Pz",
        "O1",
        "O2",
        "PO3",
        "PO4",
        "Oz"
      ],
      "temporal": [
        "T7",
        "T8",
        "TP7",
        "TP8"
      ]
    },
    "groups_realised": [
      "frontal",
      "central",
      "parietal_occipital",
      "temporal"
    ],
    "subcoord_names": [
      "m_a",
      "m_e",
      "m_o",
      "d_n",
      "d_l",
      "d_s",
      "e_e",
      "e_s",
      "e_m"
    ],
    "mean": {
      "m_a": -0.05182906612753868,
      "m_e": -0.07530243694782257,
      "m_o": 0.10609017312526703,
      "d_n": -0.13791333138942719,
      "d_l": 0.7818154096603394,
      "d_s": 0.9070699214935303,
      "e_e": 0.0,
      "e_s": 0.5883903503417969,
      "e_m": 0.0
    },
    "var": {
      "m_a": 0.003215267090126872,
      "m_e": 0.003330574370920658,
      "m_o": 0.004632158670574427,
      "d_n": 0.015384855680167675,
      "d_l": 0.02726174145936966,
      "d_s": 0.49457603693008423,
      "e_e": 0.0,
      "e_s": 0.0788026675581932,
      "e_m": 0.0
    }
  },
  "robust_summary": {
    "axes": {
      "summary": {
        "m": {
          "point": -0.38955703377723694,
          "ci_low": -0.43776294589042664,
          "ci_high": 0.41795462369918823
        },
        "d": {
          "point": 0.2327038049697876,
          "ci_low": 0.12009619921445847,
          "ci_high": 2.021449565887451
        },
        "e": {
          "point": 0.029826639220118523,
          "ci_low": -0.035867996513843536,
          "ci_high": 0.12535826861858368
        }
      },
      "reliability": {
        "m": 0.9006944183331318,
        "d": 0.7998508215852217,
        "e": 0.6170922762076149
      }
    },
    "subcoords": {
      "summary": {
        "m_a": {
          "point": -0.05242594704031944,
          "ci_low": -0.21121135354042053,
          "ci_high": 0.5562084913253784
        },
        "m_e": {
          "point": 0.031171195209026337,
          "ci_low": -0.45855703949928284,
          "ci_high": 0.10582641512155533
        },
        "m_o": {
          "point": 0.0,
          "ci_low": -0.8233788013458252,
          "ci_high": 0.44325536489486694
        },
        "d_n": {
          "point": -0.10331851243972778,
          "ci_low": -0.1613749861717224,
          "ci_high": -0.030644387006759644
        },
        "d_l": {
          "point": 0.6349300146102905,
          "ci_low": 0.4955368638038635,
          "ci_high": 2.906187057495117
        },
        "d_s": {
          "point": -0.16162091493606567,
          "ci_low": -0.3915337324142456,
          "ci_high": 3.132091760635376
        },
        "e_e": {
          "point": 0.0,
          "ci_low": -0.9989237189292908,
          "ci_high": 0.41158393025398254
        },
        "e_s": {
          "point": 1.5749293565750122,
          "ci_low": -0.6649240255355835,
          "ci_high": 1.7403661012649536
        },
        "e_m": {
          "point": 0.0,
          "ci_low": 0.0,
          "ci_high": 0.0
        }
      },
      "reliability": {
        "m_a": 0.6943261689930141,
        "m_e": 0.8948043402358866,
        "m_o": 0.9388390853813897,
        "d_n": 0.4283503207291872,
        "d_l": 0.7512504575197135,
        "d_s": 0.8634393268555237,
        "e_e": 0.9448478091864909,
        "e_s": 0.7799887377583213,
        "e_m": null
      }
    }
  },
  "dist_summary": {
    "axes": {
      "m": {
        "n": 41,
        "nan_frac": 0.0,
        "mean": -0.15253624465407395,
        "median": -0.38955703377723694,
        "std": 0.6582464422630927,
        "iqr": 0.9622484743595123,
        "mad": 0.42152807116508484,
        "mad_sigma": 0.6249575183093548,
        "skewness": -1.1221152298970698,
        "kurtosis_excess": 2.9961330874615193,
        "delta_mean_median": 0.237020789123163
      },
      "d": {
        "n": 41,
        "nan_frac": 0.0,
        "mean": 0.9187107586824312,
        "median": 0.2327038049697876,
        "std": 1.0869464634664507,
        "iqr": 2.0695906169712543,
        "mad": 0.8656249642372131,
        "mad_sigma": 1.2833755719780922,
        "skewness": 0.0395955610961618,
        "kurtosis_excess": -1.8023288608477126,
        "delta_mean_median": 0.6860069537126436
      },
      "e": {
        "n": 41,
        "nan_frac": 0.0,
        "mean": 0.1613520042709552,
        "median": 0.029826639220118523,
        "std": 0.43853936557629736,
        "iqr": 0.2782304063439369,
        "mad": 0.14940339885652065,
        "mad_sigma": 0.2215054791446775,
        "skewness": 1.6490069809039032,
        "kurtosis_excess": 2.0029771368791067,
        "delta_mean_median": 0.13152536505083667
      }
    },
    "subcoords": {
      "m_a": {
        "n": 41,
        "nan_frac": 0.0,
        "mean": -0.11596054483841105,
        "median": -0.05242594704031944,
        "std": 1.3238637267265394,
        "iqr": 0.9689777493476868,
        "mad": 0.6086344383656979,
        "mad_sigma": 0.9023614183209836,
        "skewness": -2.3734082799296927,
        "kurtosis_excess": 7.504911345075023,
        "delta_mean_median": -0.0635345977980916
      },
      "m_e": {
        "n": 41,
        "nan_frac": 0.0,
        "mean": -0.19099504191701006,
        "median": 0.031171195209026337,
        "std": 0.382311018717593,
        "iqr": 0.6017194539308548,
        "mad": 0.1751057133078575,
        "mad_sigma": 0.2596117305502295,
        "skewness": -1.4320185237369605,
        "kurtosis_excess": 3.56943465838678,
        "delta_mean_median": -0.2221662371260364
      },
      "m_o": {
        "n": 41,
        "nan_frac": 0.0,
        "mean": -0.15592426588622535,
        "median": 0.0,
        "std": 0.6840354410155379,
        "iqr": 1.3876131772994995,
        "mad": 0.6717543005943298,
        "mad_sigma": 0.9959429260611533,
        "skewness": -0.0752185985414551,
        "kurtosis_excess": -1.7474211621563664,
        "delta_mean_median": -0.15592426588622535
      },
      "d_n": {
        "n": 41,
        "nan_frac": 0.0,
        "mean": -0.012170114531749633,
        "median": -0.10331851243972778,
        "std": 0.5345653429172539,
        "iqr": 0.19405534863471985,
        "mad": 0.10608938336372375,
        "mad_sigma": 0.15728811977505683,
        "skewness": 5.50926357332892,
        "kurtosis_excess": 30.816807854648594,
        "delta_mean_median": 0.09114839790797816
      },
      "d_l": {
        "n": 41,
        "nan_frac": 0.0,
        "mean": 1.3785250775697755,
        "median": 0.6349300146102905,
        "std": 1.4665343640284931,
        "iqr": 2.73782217502594,
        "mad": 1.3180632591247559,
        "mad_sigma": 1.954160587978363,
        "skewness": -0.1005231126263067,
        "kurtosis_excess": -1.5447719737693018,
        "delta_mean_median": 0.743595062959485
      },
      "d_s": {
        "n": 41,
        "nan_frac": 0.0,
        "mean": 1.2343990224890593,
        "median": -0.16162091493606567,
        "std": 1.8530053460383853,
        "iqr": 3.710350602865219,
        "mad": 0.5874700546264648,
        "mad_sigma": 0.8709831029891967,
        "skewness": 0.14358965092541462,
        "kurtosis_excess": -1.9423397460967375,
        "delta_mean_median": 1.396019937425125
      },
      "e_e": {
        "n": 41,
        "nan_frac": 0.0,
        "mean": -0.2731739298054358,
        "median": 0.0,
        "std": 0.8248817200970119,
        "iqr": 1.5869263410568237,
        "mad": 0.674490749835968,
        "mad_sigma": 0.9999999857068061,
        "skewness": -0.19739304177195702,
        "kurtosis_excess": -1.5821244337559313,
        "delta_mean_median": -0.2731739298054358
      },
      "e_s": {
        "n": 41,
        "nan_frac": 0.0,
        "mean": 0.7577993709866594,
        "median": 1.5749293565750122,
        "std": 1.4302994638609667,
        "iqr": 2.5622265338897705,
        "mad": 0.985247015953064,
        "mad_sigma": 1.4607272258520125,
        "skewness": -0.2434914978923025,
        "kurtosis_excess": -1.564085845261213,
        "delta_mean_median": -0.8171299855883528
      },
      "e_m": {
        "n": 41,
        "nan_frac": 0.0,
        "mean": 0.14634146341463414,
        "median": 0.0,
        "std": 0.9255446810248915,
        "iqr": 0.0,
        "mad": 0.0,
        "mad_sigma": 0.0,
        "skewness": 6.166441437328339,
        "kurtosis_excess": 36.02499999999999,
        "delta_mean_median": 0.14634146341463414
      }
    }
  },
  "tau_summary": {
    "axes": {
      "m": {
        "tau_sec": 20.0,
        "dt_sec": 4.0,
        "max_lag_sec": 60.0,
        "threshold": 0.36787944117144233,
        "nan_frac": 0.0,
        "nan_policy": "strict"
      },
      "d": {
        "tau_sec": 32.0,
        "dt_sec": 4.0,
        "max_lag_sec": 60.0,
        "threshold": 0.36787944117144233,
        "nan_frac": 0.0,
        "nan_policy": "strict"
      },
      "e": {
        "tau_sec": 8.0,
        "dt_sec": 4.0,
        "max_lag_sec": 60.0,
        "threshold": 0.36787944117144233,
        "nan_frac": 0.0,
        "nan_policy": "strict"
      }
    },
    "subcoords": {
      "m_a": {
        "tau_sec": 8.0,
        "dt_sec": 4.0,
        "max_lag_sec": 60.0,
        "threshold": 0.36787944117144233,
        "nan_frac": 0.0,
        "nan_policy": "strict"
      },
      "m_e": {
        "tau_sec": 28.0,
        "dt_sec": 4.0,
        "max_lag_sec": 60.0,
        "threshold": 0.36787944117144233,
        "nan_frac": 0.0,
        "nan_policy": "strict"
      },
      "m_o": {
        "tau_sec": 32.0,
        "dt_sec": 4.0,
        "max_lag_sec": 60.0,
        "threshold": 0.36787944117144233,
        "nan_frac": 0.0,
        "nan_policy": "strict"
      },
      "d_n": {
        "tau_sec": 4.0,
        "dt_sec": 4.0,
        "max_lag_sec": 60.0,
        "threshold": 0.36787944117144233,
        "nan_frac": 0.0,
        "nan_policy": "strict"
      },
      "d_l": {
        "tau_sec": 28.0,
        "dt_sec": 4.0,
        "max_lag_sec": 60.0,
        "threshold": 0.36787944117144233,
        "nan_frac": 0.0,
        "nan_policy": "strict"
      },
      "d_s": {
        "tau_sec": 36.0,
        "dt_sec": 4.0,
        "max_lag_sec": 60.0,
        "threshold": 0.36787944117144233,
        "nan_frac": 0.0,
        "nan_policy": "strict"
      },
      "e_e": {
        "tau_sec": 32.0,
        "dt_sec": 4.0,
        "max_lag_sec": 60.0,
        "threshold": 0.36787944117144233,
        "nan_frac": 0.0,
        "nan_policy": "strict"
      },
      "e_s": {
        "tau_sec": 16.0,
        "dt_sec": 4.0,
        "max_lag_sec": 60.0,
        "threshold": 0.36787944117144233,
        "nan_frac": 0.0,
        "nan_policy": "strict"
      },
      "e_m": {
        "tau_sec": 4.0,
        "dt_sec": 4.0,
        "max_lag_sec": 60.0,
        "threshold": 0.36787944117144233,
        "nan_frac": 0.0,
        "nan_policy": "strict"
      }
    }
  },
  "tier2_jacobian": {
    "signed_divergence_balance": {
      "n": 39,
      "frac_pos": 0.0,
      "frac_neg": 1.0,
      "mean_pos": null,
      "mean_neg": -0.04146700290659329,
      "mean_abs": 0.04146700290659329
    },
    "jacobian_condition_number": {
      "n": 39,
      "nan_frac": 0.0,
      "mean": 70.67911566655046,
      "median": 47.32005634972595,
      "std": 68.65108676882576,
      "iqr": 87.16724781811205,
      "mad": 39.24066145626779,
      "mad_sigma": 58.17820467506262,
      "skewness": 1.3395253743777022,
      "kurtosis_excess": 1.499980154795944,
      "delta_mean_median": 23.359059316824506,
      "estimated_on_windows": 39,
      "total_finite_windows": 39,
      "subsampled": false
    },
    "rotation_coherence": {
      "n": 39,
      "mean_resultant_length": 0.531371625524552,
      "mean_axis": [
        -0.32521637435904993,
        0.5308454435930872,
        0.7825838133166395
      ]
    },
    "rel_mse_baseline": {
      "n": 39,
      "nan_frac": 0.0,
      "mean": 1.2120133286867387,
      "median": 1.0329298973083496,
      "std": 0.45257832683351706,
      "iqr": 0.2969919741153717,
      "mad": 0.11085766553878784,
      "mad_sigma": 0.16435757492780684,
      "skewness": 2.748544027714152,
      "kurtosis_excess": 8.275109930330485,
      "delta_mean_median": 0.1790834313783891,
      "note": "Relative local-fit MSE vs intercept-only baseline (<1 better than baseline)."
    }
  },
  "tier2_emmi": {
    "speed_mean": 0.03455988082755326,
    "speed_median": 0.022566726304061317,
    "mv_median": -0.0027038267222842193,
    "mv_abs_median": 0.0027038267222842193,
    "emmi_e_over_m_median": -0.07656552605638356,
    "mv_over_speed_median": -0.1198147522973952
  },
  "entropy_qc": {
    "e_e": {
      "var": 0.6804298521502051,
      "n_unique": 41,
      "nan_frac": 0.0,
      "provisional": false
    },
    "e_s": {
      "var": 2.045756556320969,
      "n_unique": 41,
      "nan_frac": 0.0,
      "provisional": false
    },
    "e_m": {
      "var": 0.8566329565734683,
      "n_unique": 2,
      "nan_frac": 0.0,
      "provisional": true
    }
  },
  "extensions": {
    "regional_data_available": false,
    "rfm": {
      "status": "skipped_no_regional_bold"
    },
    "o_koh": {
      "status": "skipped_no_regional_bold"
    },
    "tig": {
      "status": "skipped_no_regional_bold"
    }
  },
  "ndt_ingest": {
    "mapping_source": "mnps_projection",
    "normalize_mode_effective": "robust_z"
  },
  "mnps_3d": {
    "mode_requested": "from_v2",
    "mode_effective": "from_v2",
    "x_definition": "derived_mde_from_v2_fixed_weighted_projection",
    "from_v2": {
      "aggregation_requested": "fixed_weighted_projection",
      "aggregation": "fixed_weighted_projection",
      "legacy_pooling": "mean",
      "map": {
        "m": [
          "m_a",
          "m_e",
          "m_o"
        ],
        "d": [
          "d_n",
          "d_l",
          "d_s"
        ],
        "e": [
          "e_e",
          "e_s",
          "e_m"
        ]
      },
      "v1_mapping_source": "mnps_projection.v1_mapping",
      "v1_mapping_input": {
        "m": {
          "m_a": 0.62,
          "m_e": 0.55,
          "m_o": 0.45
        },
        "d": {
          "d_n": 0.5,
          "d_l": 0.82,
          "d_s": 0.28
        },
        "e": {
          "e_e": 0.85,
          "e_s": 0.62,
          "e_m": 0.03
        }
      },
      "v1_mapping_normalized": {
        "m": {
          "m_a": 0.6574203372001648,
          "m_e": 0.5831954479217529,
          "m_o": 0.47715988755226135
        },
        "d": {
          "d_n": 0.4998001158237457,
          "d_l": 0.819672167301178,
          "d_s": 0.2798880636692047
        },
        "e": {
          "e_e": 0.8075850605964661,
          "e_s": 0.5890620350837708,
          "e_m": 0.028503000736236572
        }
      },
      "v1_mapping_matrix": [
        [
          0.6574203372001648,
          0.0,
          0.0
        ],
        [
          0.5831954479217529,
          0.0,
          0.0
        ],
        [
          0.47715988755226135,
          0.0,
          0.0
        ],
        [
          0.0,
          0.4998001158237457,
          0.0
        ],
        [
          0.0,
          0.819672167301178,
          0.0
        ],
        [
          0.0,
          0.2798880636692047,
          0.0
        ],
        [
          0.0,
          0.0,
          0.8075850605964661
        ],
        [
          0.0,
          0.0,
          0.5890620350837708
        ],
        [
          0.0,
          0.0,
          0.028503000736236572
        ]
      ],
      "v1_mapping_matrix_rows": [
        "m_a",
        "m_e",
        "m_o",
        "d_n",
        "d_l",
        "d_s",
        "e_e",
        "e_s",
        "e_m"
      ],
      "v1_mapping_hash": "fc17689f4f8408dd321e4a6a293426ca4240892b93647558f136a277b7a7be7b",
      "fallback_reason": null
    }
  },
  "provenance": {
    "mnps_9d_definition_version": "2.0",
    "mnps_9d_constructs": {
      "e_e": {
        "intended_metric": "permutation_entropy",
        "actual_metric_used": "permutation_entropy",
        "metric_backend": "numpy",
        "params": {
          "order": 5,
          "delay": 1,
          "normalize": true
        },
        "degraded_mode": false,
        "reason": null
      }
    }
  },
  "feature_exports": {
    "raw_h5_path": "/features_raw",
    "robust_z_h5_path": "/features_robust_z",
    "scope": "all_numeric_feature_columns_excluding_metadata",
    "column_count": 68,
    "names_hash": "0cdc272fb13c2951848994e4b5bbe1ef889908219acbde8beed1cf0f5196bdeb",
    "metadata_fields": [
      "backend",
      "degraded_mode",
      "fallback_reason",
      "feature_name",
      "group_label",
      "is_regional",
      "projection_normalize_mode",
      "projection_transform_applied",
      "projection_transform_steps",
      "raw_abs_mad",
      "raw_abs_median",
      "robust_z_center",
      "robust_z_scale",
      "source_column",
      "used_anywhere",
      "used_by_coords_9d",
      "used_by_mnps_3d",
      "used_by_regional_projection"
    ]
  },
  "_TENTATIVE_NOTE": "Metrics such as tier2_jacobian, tier2_emmi, tau_summary, and dist_summary are provided as tentative QA summaries only. Real statistical verification and interpretation must be performed downstream in the analysis repository."
}