{
  "dataset_id": "ds003478:sub-012:rest_Rest_run-01",
  "samples": 129,
  "mnps": {
    "fs_out": 4.0,
    "window_sec": 8.0,
    "overlap": 0.5,
    "window_bounds": true
  },
  "mnps_axes": {
    "names": [
      "m",
      "d",
      "e"
    ],
    "meaning": {
      "m": "mobility",
      "d": "diffusivity",
      "e": "entropy"
    },
    "order": {
      "m": 0,
      "d": 1,
      "e": 2
    }
  },
  "meta_indices": {
    "mean_trace": -0.03593581178643572,
    "mean_rotation_fro": 0.12134279819630732,
    "windows": 127
  },
  "events": [],
  "labels": [],
  "jacobian": {
    "windows": 127,
    "with_centers": true
  },
  "meta_indices_v2": {
    "mean_trace": -0.021246546369749965,
    "mean_rotation_fro": 0.5324045241348386,
    "windows": 127
  },
  "jacobian_9D": {
    "windows": 127,
    "with_centers": true
  },
  "diagnostics": {
    "windows": 127.0,
    "failed": 0.0,
    "j_dot_mode": "gradient",
    "j_dot_dt": 4.0,
    "local_fit_mse_median": 0.003056075656786561,
    "local_fit_mse_baseline_median": 0.003184077562764287,
    "rel_mse_baseline_median": 0.9317477572559367
  },
  "coords_9d": {
    "names": [
      "m_a",
      "m_e",
      "m_o",
      "d_n",
      "d_l",
      "d_s",
      "e_e",
      "e_s",
      "e_m"
    ],
    "export_prefix": "v2_",
    "composites": {
      "m": "m_mean_from_v2",
      "d": "d_mean_from_v2",
      "e": "e_mean_from_v2"
    },
    "groups": {
      "m": [
        "m_a",
        "m_e",
        "m_o"
      ],
      "d": [
        "d_n",
        "d_l",
        "d_s"
      ],
      "e": [
        "e_e",
        "e_s",
        "e_m"
      ]
    }
  },
  "feature_baselines": {
    "eeg_alpha": {
      "abs_median": 0.3409678637981415,
      "abs_mad": 0.28129496242403984,
      "transformation_applied": "log10 -> robust_z -> clip_6.0"
    },
    "eeg_alpha_theta": {
      "abs_median": 0.6897006034851074,
      "abs_mad": 0.7286591353297234,
      "transformation_applied": "robust_z -> clip_6.0"
    },
    "eeg_beta": {
      "abs_median": 0.28797346353530884,
      "abs_mad": 0.13616721837222576,
      "transformation_applied": "log10 -> robust_z -> clip_6.0"
    },
    "eeg_beta_alpha": {
      "abs_median": 0.7895872592926025,
      "abs_mad": 0.5059579762637615,
      "transformation_applied": "robust_z -> clip_6.0"
    },
    "eeg_delta": {
      "abs_median": 1.16256844997406,
      "abs_mad": 1.5203929554462432,
      "transformation_applied": "log10 -> robust_z -> clip_6.0"
    },
    "eeg_gamma": {
      "abs_median": 0.09453421831130981,
      "abs_mad": 0.035131211489439006,
      "transformation_applied": "log10 -> robust_z -> clip_6.0"
    },
    "eeg_sample_entropy": {
      "abs_median": 0.886642575263977,
      "abs_mad": 0.024186561834812163,
      "transformation_applied": "robust_z -> clip_6.0"
    },
    "eeg_theta": {
      "abs_median": 0.36654531955718994,
      "abs_mad": 0.3402710979223251,
      "transformation_applied": "log10 -> robust_z -> clip_6.0"
    },
    "ecg_rmssd": {
      "abs_median": 0.22438360750675201,
      "abs_mad": 0.036820224362611766,
      "transformation_applied": "robust_z -> clip_6.0"
    },
    "eeg_hjorth_complexity": {
      "abs_median": 3.4849164485931396,
      "abs_mad": 1.6729405189990996,
      "transformation_applied": "robust_z -> clip_6.0"
    },
    "eeg_hjorth_mobility": {
      "abs_median": 0.3781859576702118,
      "abs_mad": 0.22484973932504654,
      "transformation_applied": "robust_z -> clip_6.0"
    },
    "eeg_permutation_entropy": {
      "abs_median": 0.886642575263977,
      "abs_mad": 0.024186561834812163,
      "transformation_applied": "robust_z -> clip_6.0"
    },
    "embodied_arousal_proxy": {
      "abs_median": 0.22438360750675201,
      "abs_mad": 0.036820224362611766,
      "transformation_applied": "robust_z -> clip_6.0"
    },
    "eog_blink_rate": {
      "abs_median": 0.0,
      "abs_mad": 0.0,
      "transformation_applied": "robust_z -> clip_6.0"
    }
  },
  "subject": "sub-012",
  "run": "run-01",
  "participant_meta": {
    "participant_id": "sub-012",
    "Original_ID": 518,
    "sex": 1.0,
    "age": 20.0,
    "BDI": 1.0,
    "STAI": 36.0,
    "SCID": "No Interview",
    "SCID_notes": null,
    "HamD": null
  },
  "group": "1.0",
  "condition": "rest",
  "task": "Rest",
  "coverage": {
    "rule_tag": "default",
    "min_seconds_effective": 60.0,
    "min_epochs_effective": 20,
    "seconds_effective": 520.0,
    "seconds_measured": 520.0,
    "seconds_assumed": 516.0,
    "seconds_method": "timestamps_span"
  },
  "created_at": "2026-03-09T13:43:35.877895Z",
  "jacobian_9D_blocks": {
    "config": {
      "enabled": true,
      "preset": "mde_families_v1",
      "groups": {
        "m": [
          "m_a",
          "m_e",
          "m_o"
        ],
        "d": [
          "d_n",
          "d_l",
          "d_s"
        ],
        "e": [
          "e_e",
          "e_s",
          "e_m"
        ]
      },
      "pairs": "all",
      "include_self": true,
      "include_sym_rot": true,
      "n_blocks": 9
    },
    "rows": [
      {
        "out_group": "m",
        "in_group": "m",
        "out_dim": 3,
        "in_dim": 3,
        "n_timepoints": 127,
        "block_trace_mean": -0.011394778204216497,
        "block_frobenius_mean": 0.1968274861574173,
        "block_anisotropy_mean": 92.74501808797281,
        "c_sym_mean": null,
        "c_rot_mean": null
      },
      {
        "out_group": "m",
        "in_group": "d",
        "out_dim": 3,
        "in_dim": 3,
        "n_timepoints": 127,
        "block_trace_mean": null,
        "block_frobenius_mean": 0.16571035981178284,
        "block_anisotropy_mean": null,
        "c_sym_mean": 0.1785805795899057,
        "c_rot_mean": 0.18271168183506004
      },
      {
        "out_group": "m",
        "in_group": "e",
        "out_dim": 3,
        "in_dim": 3,
        "n_timepoints": 127,
        "block_trace_mean": null,
        "block_frobenius_mean": 0.15673787891864777,
        "block_anisotropy_mean": null,
        "c_sym_mean": 0.1708433475550704,
        "c_rot_mean": 0.19126744398216564
      },
      {
        "out_group": "d",
        "in_group": "m",
        "out_dim": 3,
        "in_dim": 3,
        "n_timepoints": 127,
        "block_trace_mean": null,
        "block_frobenius_mean": 0.30798718333244324,
        "block_anisotropy_mean": null,
        "c_sym_mean": 0.1785805795899057,
        "c_rot_mean": 0.18271168183506004
      },
      {
        "out_group": "d",
        "in_group": "d",
        "out_dim": 3,
        "in_dim": 3,
        "n_timepoints": 127,
        "block_trace_mean": -0.03206076062335743,
        "block_frobenius_mean": 0.24580718576908112,
        "block_anisotropy_mean": 100.52210294918751,
        "c_sym_mean": null,
        "c_rot_mean": null
      },
      {
        "out_group": "d",
        "in_group": "e",
        "out_dim": 3,
        "in_dim": 3,
        "n_timepoints": 127,
        "block_trace_mean": null,
        "block_frobenius_mean": 0.24048803746700287,
        "block_anisotropy_mean": null,
        "c_sym_mean": 0.16901105187657312,
        "c_rot_mean": 0.18379627593506978
      },
      {
        "out_group": "e",
        "in_group": "m",
        "out_dim": 3,
        "in_dim": 3,
        "n_timepoints": 127,
        "block_trace_mean": null,
        "block_frobenius_mean": 0.3174837529659271,
        "block_anisotropy_mean": null,
        "c_sym_mean": 0.1708433475550704,
        "c_rot_mean": 0.19126744398216564
      },
      {
        "out_group": "e",
        "in_group": "d",
        "out_dim": 3,
        "in_dim": 3,
        "n_timepoints": 127,
        "block_trace_mean": null,
        "block_frobenius_mean": 0.2359839230775833,
        "block_anisotropy_mean": null,
        "c_sym_mean": 0.16901105187657312,
        "c_rot_mean": 0.18379627593506978
      },
      {
        "out_group": "e",
        "in_group": "e",
        "out_dim": 3,
        "in_dim": 3,
        "n_timepoints": 127,
        "block_trace_mean": 0.022208992875819133,
        "block_frobenius_mean": 0.1735524833202362,
        "block_anisotropy_mean": 54.67688191030908,
        "c_sym_mean": null,
        "c_rot_mean": null
      }
    ]
  },
  "ensemble_robustness": {
    "groups_config": {
      "frontal": [
        "Fp1",
        "Fp2",
        "F3",
        "F4",
        "Fz",
        "F7",
        "F8"
      ],
      "central": [
        "FC1",
        "FC2",
        "C3",
        "Cz",
        "C4"
      ],
      "parietal_occipital": [
        "P3",
        "P4",
        "Pz",
        "O1",
        "O2",
        "PO3",
        "PO4",
        "Oz"
      ],
      "temporal": [
        "T7",
        "T8",
        "TP7",
        "TP8"
      ]
    },
    "groups_realised": [
      "frontal",
      "central",
      "parietal_occipital",
      "temporal"
    ],
    "subcoord_names": [
      "m_a",
      "m_e",
      "m_o",
      "d_n",
      "d_l",
      "d_s",
      "e_e",
      "e_s",
      "e_m"
    ],
    "mean": {
      "m_a": -0.09280321002006531,
      "m_e": -0.07520603388547897,
      "m_o": 0.055448465049266815,
      "d_n": 0.01061023399233818,
      "d_l": 0.2909356355667114,
      "d_s": 0.20948641002178192,
      "e_e": 0.0,
      "e_s": 0.4230750501155853,
      "e_m": 0.0
    },
    "var": {
      "m_a": 0.006298172753304243,
      "m_e": 0.0002909330651164055,
      "m_o": 0.0010901682544499636,
      "d_n": 0.017242303118109703,
      "d_l": 0.016961773857474327,
      "d_s": 0.026385881006717682,
      "e_e": 0.0,
      "e_s": 0.006084023043513298,
      "e_m": 0.0
    }
  },
  "robust_summary": {
    "axes": {
      "summary": {
        "m": {
          "point": -0.14894917607307434,
          "ci_low": -0.22508978843688965,
          "ci_high": -0.017136717215180397
        },
        "d": {
          "point": 0.24380166828632355,
          "ci_low": -0.06872957199811935,
          "ci_high": 0.5226312279701233
        },
        "e": {
          "point": 0.20768725872039795,
          "ci_low": 0.1401410549879074,
          "ci_high": 0.26871758699417114
        }
      },
      "reliability": {
        "m": 0.7244007959975842,
        "d": 0.8709781474741802,
        "e": 0.7384962273070641
      }
    },
    "subcoords": {
      "summary": {
        "m_a": {
          "point": 0.054883867502212524,
          "ci_low": -0.07745438814163208,
          "ci_high": 0.2725578248500824
        },
        "m_e": {
          "point": -0.04245086386799812,
          "ci_low": -0.1338375210762024,
          "ci_high": -0.0018688440322875977
        },
        "m_o": {
          "point": -0.029956135898828506,
          "ci_low": -0.21393825113773346,
          "ci_high": 0.12044788897037506
        },
        "d_n": {
          "point": 0.009240895509719849,
          "ci_low": -0.0640486478805542,
          "ci_high": 0.08342781662940979
        },
        "d_l": {
          "point": 0.09597115218639374,
          "ci_low": -0.25004875659942627,
          "ci_high": 0.7296746969223022
        },
        "d_s": {
          "point": 0.07508581876754761,
          "ci_low": -0.14118734002113342,
          "ci_high": 0.4255032539367676
        },
        "e_e": {
          "point": 0.0,
          "ci_low": -0.25742319226264954,
          "ci_high": 0.16949692368507385
        },
        "e_s": {
          "point": 0.6420248746871948,
          "ci_low": 0.43014833331108093,
          "ci_high": 0.8205821514129639
        },
        "e_m": {
          "point": 0.0,
          "ci_low": -0.35037142038345337,
          "ci_high": 0.2107153683900833
        }
      },
      "reliability": {
        "m_a": 0.7687905307915811,
        "m_e": 0.8468138956801365,
        "m_o": 0.8056279047970412,
        "d_n": 0.6360943046969028,
        "d_l": 0.8717069838179953,
        "d_s": 0.8816902497305316,
        "e_e": 0.8669201210148668,
        "e_s": 0.8070178879234803,
        "e_m": 0.7764173927548732
      }
    }
  },
  "dist_summary": {
    "axes": {
      "m": {
        "n": 129,
        "nan_frac": 0.0,
        "mean": -0.06774598713458856,
        "median": -0.14894917607307434,
        "std": 0.4847097017132708,
        "iqr": 0.6549861282110214,
        "mad": 0.3212599605321884,
        "mad_sigma": 0.47630001748502254,
        "skewness": 0.5010867327877976,
        "kurtosis_excess": -0.3651863296702098,
        "delta_mean_median": 0.08120318893848578
      },
      "d": {
        "n": 129,
        "nan_frac": 0.0,
        "mean": 0.5422962707893331,
        "median": 0.24380166828632355,
        "std": 0.9994358295578637,
        "iqr": 1.6885383427143097,
        "mad": 0.6931534856557846,
        "mad_sigma": 1.0276693578332663,
        "skewness": 0.5749260125143429,
        "kurtosis_excess": -1.1293038243759574,
        "delta_mean_median": 0.2984946025030095
      },
      "e": {
        "n": 129,
        "nan_frac": 0.0,
        "mean": 0.15896668534973174,
        "median": 0.20768725872039795,
        "std": 0.35682002313311845,
        "iqr": 0.4444396775215864,
        "mad": 0.22106397151947021,
        "mad_sigma": 0.32774944417476654,
        "skewness": -0.5350395417817869,
        "kurtosis_excess": -0.2281701361580022,
        "delta_mean_median": -0.04872057337066621
      }
    },
    "subcoords": {
      "m_a": {
        "n": 129,
        "nan_frac": 0.0,
        "mean": -0.05971600217094948,
        "median": 0.054883867502212524,
        "std": 0.6509217864744429,
        "iqr": 1.0771819055080414,
        "mad": 0.537165492773056,
        "mad_sigma": 0.7964015595853329,
        "skewness": -0.39988013357391805,
        "kurtosis_excess": -0.9035041183442001,
        "delta_mean_median": -0.114599869673162
      },
      "m_e": {
        "n": 129,
        "nan_frac": 0.0,
        "mean": -0.12992151159533236,
        "median": -0.04245086386799812,
        "std": 0.47094512261265464,
        "iqr": 0.6288928836584091,
        "mad": 0.3063572160899639,
        "mad_sigma": 0.4542052085749805,
        "skewness": -0.389823574994805,
        "kurtosis_excess": -0.6816659360035118,
        "delta_mean_median": -0.08747064772733423
      },
      "m_o": {
        "n": 129,
        "nan_frac": 0.0,
        "mean": -0.00281721606576281,
        "median": -0.029956135898828506,
        "std": 0.8851657793906598,
        "iqr": 1.1486738920211792,
        "mad": 0.575010921806097,
        "mad_sigma": 0.8525111926697194,
        "skewness": 0.2226870720687491,
        "kurtosis_excess": -0.5189445690501144,
        "delta_mean_median": 0.027138919833065697
      },
      "d_n": {
        "n": 129,
        "nan_frac": 0.0,
        "mean": 0.12919077756561975,
        "median": 0.009240895509719849,
        "std": 0.5450925679942119,
        "iqr": 0.60621777176857,
        "mad": 0.2812831997871399,
        "mad_sigma": 0.41703047200441357,
        "skewness": 3.006319115126145,
        "kurtosis_excess": 16.662369912127268,
        "delta_mean_median": 0.1199498820558999
      },
      "d_l": {
        "n": 129,
        "nan_frac": 0.0,
        "mean": 0.708685735803704,
        "median": 0.09597115218639374,
        "std": 1.4856721152661425,
        "iqr": 2.6357481479644775,
        "mad": 0.8937637060880661,
        "mad_sigma": 1.3250940706461667,
        "skewness": 0.5673397665213248,
        "kurtosis_excess": -1.2170411196371862,
        "delta_mean_median": 0.6127145836173102
      },
      "d_s": {
        "n": 129,
        "nan_frac": 0.0,
        "mean": 0.7927012248325718,
        "median": 0.07508581876754761,
        "std": 1.505278837135172,
        "iqr": 2.6245299875736237,
        "mad": 0.6846755146980286,
        "mad_sigma": 1.0150999180912972,
        "skewness": 0.7355021664621012,
        "kurtosis_excess": -1.0254529914904305,
        "delta_mean_median": 0.7176154060650242
      },
      "e_e": {
        "n": 129,
        "nan_frac": 0.0,
        "mean": -0.19291003890220046,
        "median": 0.0,
        "std": 0.9482121551045182,
        "iqr": 1.5105480551719666,
        "mad": 0.674490749835968,
        "mad_sigma": 0.9999999857068061,
        "skewness": -0.48388370030201044,
        "kurtosis_excess": -0.6333605010647663,
        "delta_mean_median": -0.19291003890220046
      },
      "e_s": {
        "n": 129,
        "nan_frac": 0.0,
        "mean": 0.6552551625975112,
        "median": 0.6420248746871948,
        "std": 0.7040870285193669,
        "iqr": 1.0782609283924103,
        "mad": 0.5222967863082886,
        "mad_sigma": 0.7743572153806686,
        "skewness": 0.10576978779201368,
        "kurtosis_excess": -0.634691933378801,
        "delta_mean_median": 0.01323028791031633
      },
      "e_m": {
        "n": 129,
        "nan_frac": 0.0,
        "mean": -0.12782095068011634,
        "median": 0.0,
        "std": 0.9246342890421966,
        "iqr": 1.4612312316894531,
        "mad": 0.674490749835968,
        "mad_sigma": 0.9999999857068061,
        "skewness": -0.22059701233066156,
        "kurtosis_excess": -0.42470000751100034,
        "delta_mean_median": -0.12782095068011634
      }
    }
  },
  "tau_summary": {
    "axes": {
      "m": {
        "tau_sec": 16.0,
        "dt_sec": 4.0,
        "max_lag_sec": 60.0,
        "threshold": 0.36787944117144233,
        "nan_frac": 0.0,
        "nan_policy": "strict"
      },
      "d": {
        "tau_sec": 24.0,
        "dt_sec": 4.0,
        "max_lag_sec": 60.0,
        "threshold": 0.36787944117144233,
        "nan_frac": 0.0,
        "nan_policy": "strict"
      },
      "e": {
        "tau_sec": 16.0,
        "dt_sec": 4.0,
        "max_lag_sec": 60.0,
        "threshold": 0.36787944117144233,
        "nan_frac": 0.0,
        "nan_policy": "strict"
      }
    },
    "subcoords": {
      "m_a": {
        "tau_sec": 20.0,
        "dt_sec": 4.0,
        "max_lag_sec": 60.0,
        "threshold": 0.36787944117144233,
        "nan_frac": 0.0,
        "nan_policy": "strict"
      },
      "m_e": {
        "tau_sec": 24.0,
        "dt_sec": 4.0,
        "max_lag_sec": 60.0,
        "threshold": 0.36787944117144233,
        "nan_frac": 0.0,
        "nan_policy": "strict"
      },
      "m_o": {
        "tau_sec": 20.0,
        "dt_sec": 4.0,
        "max_lag_sec": 60.0,
        "threshold": 0.36787944117144233,
        "nan_frac": 0.0,
        "nan_policy": "strict"
      },
      "d_n": {
        "tau_sec": 8.0,
        "dt_sec": 4.0,
        "max_lag_sec": 60.0,
        "threshold": 0.36787944117144233,
        "nan_frac": 0.0,
        "nan_policy": "strict"
      },
      "d_l": {
        "tau_sec": 24.0,
        "dt_sec": 4.0,
        "max_lag_sec": 60.0,
        "threshold": 0.36787944117144233,
        "nan_frac": 0.0,
        "nan_policy": "strict"
      },
      "d_s": {
        "tau_sec": 24.0,
        "dt_sec": 4.0,
        "max_lag_sec": 60.0,
        "threshold": 0.36787944117144233,
        "nan_frac": 0.0,
        "nan_policy": "strict"
      },
      "e_e": {
        "tau_sec": 20.0,
        "dt_sec": 4.0,
        "max_lag_sec": 60.0,
        "threshold": 0.36787944117144233,
        "nan_frac": 0.0,
        "nan_policy": "strict"
      },
      "e_s": {
        "tau_sec": 20.0,
        "dt_sec": 4.0,
        "max_lag_sec": 60.0,
        "threshold": 0.36787944117144233,
        "nan_frac": 0.0,
        "nan_policy": "strict"
      },
      "e_m": {
        "tau_sec": 12.0,
        "dt_sec": 4.0,
        "max_lag_sec": 60.0,
        "threshold": 0.36787944117144233,
        "nan_frac": 0.0,
        "nan_policy": "strict"
      }
    }
  },
  "tier2_jacobian": {
    "signed_divergence_balance": {
      "n": 127,
      "frac_pos": 0.30708661417322836,
      "frac_neg": 0.6929133858267716,
      "mean_pos": 0.05662251240051447,
      "mean_neg": -0.07695597822585527,
      "mean_abs": 0.07071184305114432
    },
    "jacobian_condition_number": {
      "n": 127,
      "nan_frac": 0.0,
      "mean": 114.39287901382266,
      "median": 17.801538963817595,
      "std": 674.0310984795661,
      "iqr": 26.08147094959952,
      "mad": 10.24713457925289,
      "mad_sigma": 15.192401727200334,
      "skewness": 9.901863796968462,
      "kurtosis_excess": 101.41793317053786,
      "delta_mean_median": 96.59134005000507,
      "estimated_on_windows": 127,
      "total_finite_windows": 127,
      "subsampled": false
    },
    "rotation_coherence": {
      "n": 127,
      "mean_resultant_length": 0.5733178278048375,
      "mean_axis": [
        -0.2833896826586033,
        0.8957811859579029,
        0.3424417536552886
      ]
    },
    "rel_mse_baseline": {
      "n": 127,
      "nan_frac": 0.0,
      "mean": 0.9384443853783795,
      "median": 0.9317477345466614,
      "std": 0.09517615707802453,
      "iqr": 0.08307135105133057,
      "mad": 0.041111648082733154,
      "mad_sigma": 0.060952129447460174,
      "skewness": 1.750702407768204,
      "kurtosis_excess": 4.850265492739583,
      "delta_mean_median": 0.0066966508317181095,
      "note": "Relative local-fit MSE vs intercept-only baseline (<1 better than baseline)."
    }
  },
  "tier2_emmi": {
    "speed_mean": 0.08464014434759626,
    "speed_median": 0.07140042874926143,
    "mv_median": -0.007541967079383162,
    "mv_abs_median": 0.007541967079383162,
    "emmi_e_over_m_median": -1.394349832579851,
    "mv_over_speed_median": -0.10562915673613761
  },
  "entropy_qc": {
    "e_e": {
      "var": 0.8991062910879548,
      "n_unique": 129,
      "nan_frac": 0.0,
      "provisional": false
    },
    "e_s": {
      "var": 0.4957385437292318,
      "n_unique": 129,
      "nan_frac": 0.0,
      "provisional": false
    },
    "e_m": {
      "var": 0.8549485684725683,
      "n_unique": 129,
      "nan_frac": 0.0,
      "provisional": false
    }
  },
  "extensions": {
    "regional_data_available": false,
    "rfm": {
      "status": "skipped_no_regional_bold"
    },
    "o_koh": {
      "status": "skipped_no_regional_bold"
    },
    "tig": {
      "status": "skipped_no_regional_bold"
    }
  },
  "ndt_ingest": {
    "mapping_source": "mnps_projection",
    "normalize_mode_effective": "robust_z"
  },
  "mnps_3d": {
    "mode_requested": "from_v2",
    "mode_effective": "from_v2",
    "x_definition": "derived_mde_from_v2_fixed_weighted_projection",
    "from_v2": {
      "aggregation_requested": "fixed_weighted_projection",
      "aggregation": "fixed_weighted_projection",
      "legacy_pooling": "mean",
      "map": {
        "m": [
          "m_a",
          "m_e",
          "m_o"
        ],
        "d": [
          "d_n",
          "d_l",
          "d_s"
        ],
        "e": [
          "e_e",
          "e_s",
          "e_m"
        ]
      },
      "v1_mapping_source": "mnps_projection.v1_mapping",
      "v1_mapping_input": {
        "m": {
          "m_a": 0.62,
          "m_e": 0.55,
          "m_o": 0.45
        },
        "d": {
          "d_n": 0.5,
          "d_l": 0.82,
          "d_s": 0.28
        },
        "e": {
          "e_e": 0.85,
          "e_s": 0.62,
          "e_m": 0.03
        }
      },
      "v1_mapping_normalized": {
        "m": {
          "m_a": 0.6574203372001648,
          "m_e": 0.5831954479217529,
          "m_o": 0.47715988755226135
        },
        "d": {
          "d_n": 0.4998001158237457,
          "d_l": 0.819672167301178,
          "d_s": 0.2798880636692047
        },
        "e": {
          "e_e": 0.8075850605964661,
          "e_s": 0.5890620350837708,
          "e_m": 0.028503000736236572
        }
      },
      "v1_mapping_matrix": [
        [
          0.6574203372001648,
          0.0,
          0.0
        ],
        [
          0.5831954479217529,
          0.0,
          0.0
        ],
        [
          0.47715988755226135,
          0.0,
          0.0
        ],
        [
          0.0,
          0.4998001158237457,
          0.0
        ],
        [
          0.0,
          0.819672167301178,
          0.0
        ],
        [
          0.0,
          0.2798880636692047,
          0.0
        ],
        [
          0.0,
          0.0,
          0.8075850605964661
        ],
        [
          0.0,
          0.0,
          0.5890620350837708
        ],
        [
          0.0,
          0.0,
          0.028503000736236572
        ]
      ],
      "v1_mapping_matrix_rows": [
        "m_a",
        "m_e",
        "m_o",
        "d_n",
        "d_l",
        "d_s",
        "e_e",
        "e_s",
        "e_m"
      ],
      "v1_mapping_hash": "fc17689f4f8408dd321e4a6a293426ca4240892b93647558f136a277b7a7be7b",
      "fallback_reason": null
    }
  },
  "provenance": {
    "mnps_9d_definition_version": "2.0",
    "mnps_9d_constructs": {
      "e_e": {
        "intended_metric": "permutation_entropy",
        "actual_metric_used": "permutation_entropy",
        "metric_backend": "numpy",
        "params": {
          "order": 5,
          "delay": 1,
          "normalize": true
        },
        "degraded_mode": false,
        "reason": null
      }
    }
  },
  "feature_exports": {
    "raw_h5_path": "/features_raw",
    "robust_z_h5_path": "/features_robust_z",
    "scope": "all_numeric_feature_columns_excluding_metadata",
    "column_count": 68,
    "names_hash": "0cdc272fb13c2951848994e4b5bbe1ef889908219acbde8beed1cf0f5196bdeb",
    "metadata_fields": [
      "backend",
      "degraded_mode",
      "fallback_reason",
      "feature_name",
      "group_label",
      "is_regional",
      "projection_normalize_mode",
      "projection_transform_applied",
      "projection_transform_steps",
      "raw_abs_mad",
      "raw_abs_median",
      "robust_z_center",
      "robust_z_scale",
      "source_column",
      "used_anywhere",
      "used_by_coords_9d",
      "used_by_mnps_3d",
      "used_by_regional_projection"
    ]
  },
  "_TENTATIVE_NOTE": "Metrics such as tier2_jacobian, tier2_emmi, tau_summary, and dist_summary are provided as tentative QA summaries only. Real statistical verification and interpretation must be performed downstream in the analysis repository."
}