{
  "dataset_id": "ds003478:sub-049:rest_Rest_run-02",
  "samples": 41,
  "mnps": {
    "fs_out": 4.0,
    "window_sec": 8.0,
    "overlap": 0.5,
    "window_bounds": true
  },
  "mnps_axes": {
    "names": [
      "m",
      "d",
      "e"
    ],
    "meaning": {
      "m": "mobility",
      "d": "diffusivity",
      "e": "entropy"
    },
    "order": {
      "m": 0,
      "d": 1,
      "e": 2
    }
  },
  "meta_indices": {
    "mean_trace": -0.0066443066088817055,
    "mean_rotation_fro": 0.08537879700844105,
    "windows": 39
  },
  "events": [],
  "labels": [],
  "jacobian": {
    "windows": 39,
    "with_centers": true
  },
  "meta_indices_v2": {
    "mean_trace": 0.06158306468755771,
    "mean_rotation_fro": 0.4235569200454614,
    "windows": 39
  },
  "jacobian_9D": {
    "windows": 39,
    "with_centers": true
  },
  "diagnostics": {
    "windows": 39.0,
    "failed": 0.0,
    "j_dot_mode": "gradient",
    "j_dot_dt": 4.0,
    "local_fit_mse_median": 0.0021863984875380993,
    "local_fit_mse_baseline_median": 0.0023973218630999327,
    "rel_mse_baseline_median": 0.8211663319540818
  },
  "coords_9d": {
    "names": [
      "m_a",
      "m_e",
      "m_o",
      "d_n",
      "d_l",
      "d_s",
      "e_e",
      "e_s",
      "e_m"
    ],
    "export_prefix": "v2_",
    "composites": {
      "m": "m_mean_from_v2",
      "d": "d_mean_from_v2",
      "e": "e_mean_from_v2"
    },
    "groups": {
      "m": [
        "m_a",
        "m_e",
        "m_o"
      ],
      "d": [
        "d_n",
        "d_l",
        "d_s"
      ],
      "e": [
        "e_e",
        "e_s",
        "e_m"
      ]
    }
  },
  "feature_baselines": {
    "eeg_alpha": {
      "abs_median": 0.7194424867630005,
      "abs_mad": 0.7654818782329559,
      "transformation_applied": "log10 -> robust_z -> clip_6.0"
    },
    "eeg_alpha_theta": {
      "abs_median": 2.0011703968048096,
      "abs_mad": 1.203888043999672,
      "transformation_applied": "robust_z -> clip_6.0"
    },
    "eeg_beta": {
      "abs_median": 0.47924286127090454,
      "abs_mad": 0.2611958594620228,
      "transformation_applied": "log10 -> robust_z -> clip_6.0"
    },
    "eeg_beta_alpha": {
      "abs_median": 0.6378931403160095,
      "abs_mad": 0.3754255064964294,
      "transformation_applied": "robust_z -> clip_6.0"
    },
    "eeg_delta": {
      "abs_median": 0.44545844197273254,
      "abs_mad": 0.32151937000751496,
      "transformation_applied": "log10 -> robust_z -> clip_6.0"
    },
    "eeg_gamma": {
      "abs_median": 0.18699005246162415,
      "abs_mad": 0.05788998171687126,
      "transformation_applied": "log10 -> robust_z -> clip_6.0"
    },
    "eeg_sample_entropy": {
      "abs_median": 0.8762406706809998,
      "abs_mad": 0.02936653711795807,
      "transformation_applied": "robust_z -> clip_6.0"
    },
    "eeg_theta": {
      "abs_median": 0.42470690608024597,
      "abs_mad": 0.34306389436125756,
      "transformation_applied": "log10 -> robust_z -> clip_6.0"
    },
    "ecg_rmssd": {
      "abs_median": null,
      "abs_mad": null,
      "transformation_applied": "none"
    },
    "eeg_hjorth_complexity": {
      "abs_median": 2.5982279777526855,
      "abs_mad": 0.33218366632461543,
      "transformation_applied": "robust_z -> clip_6.0"
    },
    "eeg_hjorth_mobility": {
      "abs_median": 0.47704964876174927,
      "abs_mad": 0.0701953944504261,
      "transformation_applied": "robust_z -> clip_6.0"
    },
    "eeg_permutation_entropy": {
      "abs_median": 0.8762406706809998,
      "abs_mad": 0.02936653711795807,
      "transformation_applied": "robust_z -> clip_6.0"
    },
    "embodied_arousal_proxy": {
      "abs_median": 0.0,
      "abs_mad": 0.0,
      "transformation_applied": "robust_z -> clip_6.0"
    },
    "eog_blink_rate": {
      "abs_median": 0.0,
      "abs_mad": 0.0,
      "transformation_applied": "robust_z -> clip_6.0"
    }
  },
  "subject": "sub-049",
  "run": "run-02",
  "participant_meta": {
    "participant_id": "sub-049",
    "Original_ID": 555,
    "sex": 1.0,
    "age": 18.0,
    "BDI": 1.0,
    "STAI": 29.0,
    "SCID": "No Interview",
    "SCID_notes": null,
    "HamD": null
  },
  "group": "1.0",
  "condition": "rest",
  "task": "Rest",
  "coverage": {
    "rule_tag": "default",
    "min_seconds_effective": 60.0,
    "min_epochs_effective": 20,
    "seconds_effective": 168.0,
    "seconds_measured": 168.0,
    "seconds_assumed": 164.0,
    "seconds_method": "timestamps_span"
  },
  "created_at": "2026-03-09T13:49:56.898547Z",
  "jacobian_9D_blocks": {
    "config": {
      "enabled": true,
      "preset": "mde_families_v1",
      "groups": {
        "m": [
          "m_a",
          "m_e",
          "m_o"
        ],
        "d": [
          "d_n",
          "d_l",
          "d_s"
        ],
        "e": [
          "e_e",
          "e_s",
          "e_m"
        ]
      },
      "pairs": "all",
      "include_self": true,
      "include_sym_rot": true,
      "n_blocks": 9
    },
    "rows": [
      {
        "out_group": "m",
        "in_group": "m",
        "out_dim": 3,
        "in_dim": 3,
        "n_timepoints": 39,
        "block_trace_mean": 0.09348305883124852,
        "block_frobenius_mean": 0.22484645247459412,
        "block_anisotropy_mean": 185.41115612861438,
        "c_sym_mean": null,
        "c_rot_mean": null
      },
      {
        "out_group": "m",
        "in_group": "d",
        "out_dim": 3,
        "in_dim": 3,
        "n_timepoints": 39,
        "block_trace_mean": null,
        "block_frobenius_mean": 0.2223629355430603,
        "block_anisotropy_mean": null,
        "c_sym_mean": 0.17088082891244155,
        "c_rot_mean": 0.19007966782038027
      },
      {
        "out_group": "m",
        "in_group": "e",
        "out_dim": 3,
        "in_dim": 3,
        "n_timepoints": 39,
        "block_trace_mean": null,
        "block_frobenius_mean": 0.1361294984817505,
        "block_anisotropy_mean": null,
        "c_sym_mean": 0.1075133692759734,
        "c_rot_mean": 0.10992497989000419
      },
      {
        "out_group": "d",
        "in_group": "m",
        "out_dim": 3,
        "in_dim": 3,
        "n_timepoints": 39,
        "block_trace_mean": null,
        "block_frobenius_mean": 0.2821216583251953,
        "block_anisotropy_mean": null,
        "c_sym_mean": 0.17088082891244155,
        "c_rot_mean": 0.19007966782038027
      },
      {
        "out_group": "d",
        "in_group": "d",
        "out_dim": 3,
        "in_dim": 3,
        "n_timepoints": 39,
        "block_trace_mean": 0.03835922355453173,
        "block_frobenius_mean": 0.2762363851070404,
        "block_anisotropy_mean": 397.39058970182367,
        "c_sym_mean": null,
        "c_rot_mean": null
      },
      {
        "out_group": "d",
        "in_group": "e",
        "out_dim": 3,
        "in_dim": 3,
        "n_timepoints": 39,
        "block_trace_mean": null,
        "block_frobenius_mean": 0.1481667011976242,
        "block_anisotropy_mean": null,
        "c_sym_mean": 0.11766185133885114,
        "c_rot_mean": 0.11045711907820824
      },
      {
        "out_group": "e",
        "in_group": "m",
        "out_dim": 3,
        "in_dim": 3,
        "n_timepoints": 39,
        "block_trace_mean": null,
        "block_frobenius_mean": 0.16740526258945465,
        "block_anisotropy_mean": null,
        "c_sym_mean": 0.1075133692759734,
        "c_rot_mean": 0.10992497989000419
      },
      {
        "out_group": "e",
        "in_group": "d",
        "out_dim": 3,
        "in_dim": 3,
        "n_timepoints": 39,
        "block_trace_mean": null,
        "block_frobenius_mean": 0.17099358141422272,
        "block_anisotropy_mean": null,
        "c_sym_mean": 0.11766185133885114,
        "c_rot_mean": 0.11045711907820824
      },
      {
        "out_group": "e",
        "in_group": "e",
        "out_dim": 3,
        "in_dim": 3,
        "n_timepoints": 39,
        "block_trace_mean": -0.07025921774598268,
        "block_frobenius_mean": 0.07907013595104218,
        "block_anisotropy_mean": null,
        "c_sym_mean": null,
        "c_rot_mean": null
      }
    ]
  },
  "ensemble_robustness": {
    "groups_config": {
      "frontal": [
        "Fp1",
        "Fp2",
        "F3",
        "F4",
        "Fz",
        "F7",
        "F8"
      ],
      "central": [
        "FC1",
        "FC2",
        "C3",
        "Cz",
        "C4"
      ],
      "parietal_occipital": [
        "P3",
        "P4",
        "Pz",
        "O1",
        "O2",
        "PO3",
        "PO4",
        "Oz"
      ],
      "temporal": [
        "T7",
        "T8",
        "TP7",
        "TP8"
      ]
    },
    "groups_realised": [
      "frontal",
      "central",
      "parietal_occipital",
      "temporal"
    ],
    "subcoord_names": [
      "m_a",
      "m_e",
      "m_o",
      "d_n",
      "d_l",
      "d_s",
      "e_e",
      "e_s",
      "e_m"
    ],
    "mean": {
      "m_a": -0.15170195698738098,
      "m_e": -0.07146617025136948,
      "m_o": -0.039500847458839417,
      "d_n": 0.09395211935043335,
      "d_l": 0.11417609453201294,
      "d_s": 0.2513125538825989,
      "e_e": 0.0,
      "e_s": 0.0939614325761795,
      "e_m": 0.0
    },
    "var": {
      "m_a": 0.002438211115077138,
      "m_e": 0.0012506789062172174,
      "m_o": 0.002579987980425358,
      "d_n": 0.013295941986143589,
      "d_l": 0.0028394784312695265,
      "d_s": 0.008065354079008102,
      "e_e": 0.0,
      "e_s": 0.010799220763146877,
      "e_m": 0.0
    }
  },
  "robust_summary": {
    "axes": {
      "summary": {
        "m": {
          "point": -0.060195740312337875,
          "ci_low": -0.3246195316314697,
          "ci_high": 0.27950552105903625
        },
        "d": {
          "point": 0.11001534014940262,
          "ci_low": 0.02318417653441429,
          "ci_high": 0.26436686515808105
        },
        "e": {
          "point": -0.10251915454864502,
          "ci_low": -0.2572586238384247,
          "ci_high": 0.04272233322262764
        }
      },
      "reliability": {
        "m": 0.646956469988623,
        "d": 0.5905727308540434,
        "e": 0.833871566390336
      }
    },
    "subcoords": {
      "summary": {
        "m_a": {
          "point": -0.10957150906324387,
          "ci_low": -0.42790067195892334,
          "ci_high": 0.4237059950828552
        },
        "m_e": {
          "point": -0.07880879938602448,
          "ci_low": -0.23139126598834991,
          "ci_high": 0.14785850048065186
        },
        "m_o": {
          "point": -0.028385119512677193,
          "ci_low": -0.4727341830730438,
          "ci_high": 0.5408428311347961
        },
        "d_n": {
          "point": 0.0031870752573013306,
          "ci_low": -0.20302289724349976,
          "ci_high": 0.2111223340034485
        },
        "d_l": {
          "point": 0.3494182825088501,
          "ci_low": -0.01847732812166214,
          "ci_high": 0.5043870210647583
        },
        "d_s": {
          "point": 0.03091089054942131,
          "ci_low": -0.40657180547714233,
          "ci_high": 0.3089156746864319
        },
        "e_e": {
          "point": 0.0,
          "ci_low": -0.6080979108810425,
          "ci_high": 0.4530811905860901
        },
        "e_s": {
          "point": 0.07568219304084778,
          "ci_low": -0.34057071805000305,
          "ci_high": 0.4198099374771118
        },
        "e_m": {
          "point": 0.0,
          "ci_low": 0.0,
          "ci_high": 0.0
        }
      },
      "reliability": {
        "m_a": 0.6612414112450044,
        "m_e": 0.66552712329493,
        "m_o": 0.6622632847834369,
        "d_n": 0.6151895813116486,
        "d_l": 0.7246289932375122,
        "d_s": 0.605431929849208,
        "e_e": 0.892402441163454,
        "e_s": 0.5959393781927325,
        "e_m": null
      }
    }
  },
  "dist_summary": {
    "axes": {
      "m": {
        "n": 41,
        "nan_frac": 0.0,
        "mean": 0.0638466729078351,
        "median": -0.060195740312337875,
        "std": 0.6776771061871022,
        "iqr": 0.7335768640041351,
        "mad": 0.37749310955405235,
        "mad_sigma": 0.559671284224838,
        "skewness": 0.009174584629167721,
        "kurtosis_excess": 1.4752886941837353,
        "delta_mean_median": 0.12404241322017298
      },
      "d": {
        "n": 41,
        "nan_frac": 0.0,
        "mean": 0.22848554258163814,
        "median": 0.11001534014940262,
        "std": 0.5702388124596789,
        "iqr": 0.3700047507882118,
        "mad": 0.19129618257284164,
        "mad_sigma": 0.283615720282495,
        "skewness": 3.050500615861121,
        "kurtosis_excess": 13.940930241638004,
        "delta_mean_median": 0.11847020243223552
      },
      "e": {
        "n": 41,
        "nan_frac": 0.0,
        "mean": 0.0076303805761243695,
        "median": -0.10251915454864502,
        "std": 0.5525052085406318,
        "iqr": 0.5687898397445679,
        "mad": 0.29131925106048584,
        "mad_sigma": 0.43190992162227626,
        "skewness": 1.4895258795161395,
        "kurtosis_excess": 2.483686386483301,
        "delta_mean_median": 0.11014953512476938
      }
    },
    "subcoords": {
      "m_a": {
        "n": 41,
        "nan_frac": 0.0,
        "mean": -0.1296964981025312,
        "median": -0.10957150906324387,
        "std": 1.2134976806474,
        "iqr": 1.3499547839164734,
        "mad": 0.5569591745734215,
        "mad_sigma": 0.8257476722225546,
        "skewness": -2.784934691232682,
        "kurtosis_excess": 11.015051363551526,
        "delta_mean_median": -0.020124989039287333
      },
      "m_e": {
        "n": 41,
        "nan_frac": 0.0,
        "mean": -0.01008136656771346,
        "median": -0.07880879938602448,
        "std": 0.4906630531086042,
        "iqr": 0.552399605512619,
        "mad": 0.2588937133550644,
        "mad_sigma": 0.38383581942021844,
        "skewness": -1.2098630770997205,
        "kurtosis_excess": 4.5193120629807995,
        "delta_mean_median": 0.06872743281831102
      },
      "m_o": {
        "n": 41,
        "nan_frac": 0.0,
        "mean": 0.42086267312307185,
        "median": -0.028385119512677193,
        "std": 1.3054189126181122,
        "iqr": 1.7730898261070251,
        "mad": 0.6813322734087706,
        "mad_sigma": 1.0101432285558432,
        "skewness": 1.026973467452474,
        "kurtosis_excess": -0.022875744159121858,
        "delta_mean_median": 0.44924779263574904
      },
      "d_n": {
        "n": 41,
        "nan_frac": 0.0,
        "mean": 0.31921725175002724,
        "median": 0.0031870752573013306,
        "std": 1.1309283171471762,
        "iqr": 0.6028150916099548,
        "mad": 0.24968738853931427,
        "mad_sigma": 0.37018652224838733,
        "skewness": 1.893560506812544,
        "kurtosis_excess": 4.550165832801002,
        "delta_mean_median": 0.3160301764927259
      },
      "d_l": {
        "n": 41,
        "nan_frac": 0.0,
        "mean": 0.24315579140149965,
        "median": 0.3494182825088501,
        "std": 0.8441193651914413,
        "iqr": 0.760204017162323,
        "mad": 0.35229402780532837,
        "mad_sigma": 0.5223111256241798,
        "skewness": 0.04077598152086216,
        "kurtosis_excess": 0.8052622046951532,
        "delta_mean_median": -0.10626249110735045
      },
      "d_s": {
        "n": 41,
        "nan_frac": 0.0,
        "mean": 0.023501781701314742,
        "median": 0.03091089054942131,
        "std": 0.8290796064490596,
        "iqr": 1.2099127769470215,
        "mad": 0.6075459532439709,
        "mad_sigma": 0.9007476302795112,
        "skewness": 0.3105187854102697,
        "kurtosis_excess": 0.10429058488304577,
        "delta_mean_median": -0.007409108848106569
      },
      "e_e": {
        "n": 41,
        "nan_frac": 0.0,
        "mean": -0.012600296245115558,
        "median": 0.0,
        "std": 0.8909321572819875,
        "iqr": 1.2857346534729004,
        "mad": 0.674490749835968,
        "mad_sigma": 0.9999999857068061,
        "skewness": 0.42027220313232155,
        "kurtosis_excess": -0.022078672856370662,
        "delta_mean_median": -0.012600296245115558
      },
      "e_s": {
        "n": 41,
        "nan_frac": 0.0,
        "mean": 0.028654164112195735,
        "median": 0.07568219304084778,
        "std": 0.7972698409174201,
        "iqr": 0.9137130379676819,
        "mad": 0.47654950618743896,
        "mad_sigma": 0.7065322978734969,
        "skewness": 0.9194864811715147,
        "kurtosis_excess": 3.0298484101356937,
        "delta_mean_median": -0.047028028928652044
      },
      "e_m": {
        "n": 41,
        "nan_frac": 0.0,
        "mean": 0.14634146341463414,
        "median": 0.0,
        "std": 0.9255446810248915,
        "iqr": 0.0,
        "mad": 0.0,
        "mad_sigma": 0.0,
        "skewness": 6.166441437328339,
        "kurtosis_excess": 36.02499999999999,
        "delta_mean_median": 0.14634146341463414
      }
    }
  },
  "tau_summary": {
    "axes": {
      "m": {
        "tau_sec": 16.0,
        "dt_sec": 4.0,
        "max_lag_sec": 60.0,
        "threshold": 0.36787944117144233,
        "nan_frac": 0.0,
        "nan_policy": "strict"
      },
      "d": {
        "tau_sec": 4.0,
        "dt_sec": 4.0,
        "max_lag_sec": 60.0,
        "threshold": 0.36787944117144233,
        "nan_frac": 0.0,
        "nan_policy": "strict"
      },
      "e": {
        "tau_sec": 12.0,
        "dt_sec": 4.0,
        "max_lag_sec": 60.0,
        "threshold": 0.36787944117144233,
        "nan_frac": 0.0,
        "nan_policy": "strict"
      }
    },
    "subcoords": {
      "m_a": {
        "tau_sec": 4.0,
        "dt_sec": 4.0,
        "max_lag_sec": 60.0,
        "threshold": 0.36787944117144233,
        "nan_frac": 0.0,
        "nan_policy": "strict"
      },
      "m_e": {
        "tau_sec": 8.0,
        "dt_sec": 4.0,
        "max_lag_sec": 60.0,
        "threshold": 0.36787944117144233,
        "nan_frac": 0.0,
        "nan_policy": "strict"
      },
      "m_o": {
        "tau_sec": 12.0,
        "dt_sec": 4.0,
        "max_lag_sec": 60.0,
        "threshold": 0.36787944117144233,
        "nan_frac": 0.0,
        "nan_policy": "strict"
      },
      "d_n": {
        "tau_sec": 4.0,
        "dt_sec": 4.0,
        "max_lag_sec": 60.0,
        "threshold": 0.36787944117144233,
        "nan_frac": 0.0,
        "nan_policy": "strict"
      },
      "d_l": {
        "tau_sec": 8.0,
        "dt_sec": 4.0,
        "max_lag_sec": 60.0,
        "threshold": 0.36787944117144233,
        "nan_frac": 0.0,
        "nan_policy": "strict"
      },
      "d_s": {
        "tau_sec": 8.0,
        "dt_sec": 4.0,
        "max_lag_sec": 60.0,
        "threshold": 0.36787944117144233,
        "nan_frac": 0.0,
        "nan_policy": "strict"
      },
      "e_e": {
        "tau_sec": 20.0,
        "dt_sec": 4.0,
        "max_lag_sec": 60.0,
        "threshold": 0.36787944117144233,
        "nan_frac": 0.0,
        "nan_policy": "strict"
      },
      "e_s": {
        "tau_sec": 12.0,
        "dt_sec": 4.0,
        "max_lag_sec": 60.0,
        "threshold": 0.36787944117144233,
        "nan_frac": 0.0,
        "nan_policy": "strict"
      },
      "e_m": {
        "tau_sec": 4.0,
        "dt_sec": 4.0,
        "max_lag_sec": 60.0,
        "threshold": 0.36787944117144233,
        "nan_frac": 0.0,
        "nan_policy": "strict"
      }
    }
  },
  "tier2_jacobian": {
    "signed_divergence_balance": {
      "n": 39,
      "frac_pos": 0.4358974358974359,
      "frac_neg": 0.5641025641025641,
      "mean_pos": 0.044431010672055626,
      "mean_neg": -0.04611159712625191,
      "mean_abs": 0.045379033800063785
    },
    "jacobian_condition_number": {
      "n": 39,
      "nan_frac": 0.0,
      "mean": 35.17023274044828,
      "median": 9.029041601818452,
      "std": 142.99034124357394,
      "iqr": 6.909883239391657,
      "mad": 3.4528888806424254,
      "mad_sigma": 5.11925305444046,
      "skewness": 5.865813264269311,
      "kurtosis_excess": 32.8900413886658,
      "delta_mean_median": 26.141191138629825,
      "estimated_on_windows": 39,
      "total_finite_windows": 39,
      "subsampled": false
    },
    "rotation_coherence": {
      "n": 39,
      "mean_resultant_length": 0.7405525090658324,
      "mean_axis": [
        0.1759042488826483,
        -0.5785131997282842,
        0.7964798635026336
      ]
    },
    "rel_mse_baseline": {
      "n": 39,
      "nan_frac": 0.0,
      "mean": 0.8388474782307943,
      "median": 0.8211663365364075,
      "std": 0.09742459565137758,
      "iqr": 0.11081305146217346,
      "mad": 0.05273491144180298,
      "mad_sigma": 0.07818477970361709,
      "skewness": 1.7274799579483981,
      "kurtosis_excess": 5.31044133934042,
      "delta_mean_median": 0.017681141694386837,
      "note": "Relative local-fit MSE vs intercept-only baseline (<1 better than baseline)."
    }
  },
  "tier2_emmi": {
    "speed_mean": 0.08228370584363891,
    "speed_median": 0.07892830268221929,
    "mv_median": 0.0006789284718492106,
    "mv_abs_median": 0.0006789284718492106,
    "emmi_e_over_m_median": 1.7030964984682218,
    "mv_over_speed_median": 0.008601837981778333
  },
  "entropy_qc": {
    "e_e": {
      "var": 0.7937601088791362,
      "n_unique": 41,
      "nan_frac": 0.0,
      "provisional": false
    },
    "e_s": {
      "var": 0.6356391992364885,
      "n_unique": 41,
      "nan_frac": 0.0,
      "provisional": false
    },
    "e_m": {
      "var": 0.8566329565734683,
      "n_unique": 2,
      "nan_frac": 0.0,
      "provisional": true
    }
  },
  "extensions": {
    "regional_data_available": false,
    "rfm": {
      "status": "skipped_no_regional_bold"
    },
    "o_koh": {
      "status": "skipped_no_regional_bold"
    },
    "tig": {
      "status": "skipped_no_regional_bold"
    }
  },
  "ndt_ingest": {
    "mapping_source": "mnps_projection",
    "normalize_mode_effective": "robust_z"
  },
  "mnps_3d": {
    "mode_requested": "from_v2",
    "mode_effective": "from_v2",
    "x_definition": "derived_mde_from_v2_fixed_weighted_projection",
    "from_v2": {
      "aggregation_requested": "fixed_weighted_projection",
      "aggregation": "fixed_weighted_projection",
      "legacy_pooling": "mean",
      "map": {
        "m": [
          "m_a",
          "m_e",
          "m_o"
        ],
        "d": [
          "d_n",
          "d_l",
          "d_s"
        ],
        "e": [
          "e_e",
          "e_s",
          "e_m"
        ]
      },
      "v1_mapping_source": "mnps_projection.v1_mapping",
      "v1_mapping_input": {
        "m": {
          "m_a": 0.62,
          "m_e": 0.55,
          "m_o": 0.45
        },
        "d": {
          "d_n": 0.5,
          "d_l": 0.82,
          "d_s": 0.28
        },
        "e": {
          "e_e": 0.85,
          "e_s": 0.62,
          "e_m": 0.03
        }
      },
      "v1_mapping_normalized": {
        "m": {
          "m_a": 0.6574203372001648,
          "m_e": 0.5831954479217529,
          "m_o": 0.47715988755226135
        },
        "d": {
          "d_n": 0.4998001158237457,
          "d_l": 0.819672167301178,
          "d_s": 0.2798880636692047
        },
        "e": {
          "e_e": 0.8075850605964661,
          "e_s": 0.5890620350837708,
          "e_m": 0.028503000736236572
        }
      },
      "v1_mapping_matrix": [
        [
          0.6574203372001648,
          0.0,
          0.0
        ],
        [
          0.5831954479217529,
          0.0,
          0.0
        ],
        [
          0.47715988755226135,
          0.0,
          0.0
        ],
        [
          0.0,
          0.4998001158237457,
          0.0
        ],
        [
          0.0,
          0.819672167301178,
          0.0
        ],
        [
          0.0,
          0.2798880636692047,
          0.0
        ],
        [
          0.0,
          0.0,
          0.8075850605964661
        ],
        [
          0.0,
          0.0,
          0.5890620350837708
        ],
        [
          0.0,
          0.0,
          0.028503000736236572
        ]
      ],
      "v1_mapping_matrix_rows": [
        "m_a",
        "m_e",
        "m_o",
        "d_n",
        "d_l",
        "d_s",
        "e_e",
        "e_s",
        "e_m"
      ],
      "v1_mapping_hash": "fc17689f4f8408dd321e4a6a293426ca4240892b93647558f136a277b7a7be7b",
      "fallback_reason": null
    }
  },
  "provenance": {
    "mnps_9d_definition_version": "2.0",
    "mnps_9d_constructs": {
      "e_e": {
        "intended_metric": "permutation_entropy",
        "actual_metric_used": "permutation_entropy",
        "metric_backend": "numpy",
        "params": {
          "order": 5,
          "delay": 1,
          "normalize": true
        },
        "degraded_mode": false,
        "reason": null
      }
    }
  },
  "feature_exports": {
    "raw_h5_path": "/features_raw",
    "robust_z_h5_path": "/features_robust_z",
    "scope": "all_numeric_feature_columns_excluding_metadata",
    "column_count": 68,
    "names_hash": "0cdc272fb13c2951848994e4b5bbe1ef889908219acbde8beed1cf0f5196bdeb",
    "metadata_fields": [
      "backend",
      "degraded_mode",
      "fallback_reason",
      "feature_name",
      "group_label",
      "is_regional",
      "projection_normalize_mode",
      "projection_transform_applied",
      "projection_transform_steps",
      "raw_abs_mad",
      "raw_abs_median",
      "robust_z_center",
      "robust_z_scale",
      "source_column",
      "used_anywhere",
      "used_by_coords_9d",
      "used_by_mnps_3d",
      "used_by_regional_projection"
    ]
  },
  "_TENTATIVE_NOTE": "Metrics such as tier2_jacobian, tier2_emmi, tau_summary, and dist_summary are provided as tentative QA summaries only. Real statistical verification and interpretation must be performed downstream in the analysis repository."
}